CHANGES.rst
MANIFEST.in
README.rst
setup.py
blockreferralspam/__init__.py
blockreferralspam/__init__.pyc
blockreferralspam/admin.pyc
blockreferralspam/middleware.py
blockreferralspam/middleware.pyc
blockreferralspam/models.py
blockreferralspam/models.pyc
blockreferralspam/spammers.txt
blockreferralspam/tests.py
blockreferralspam/tests.pyc
django_blockreferralspam.egg-info/PKG-INFO
django_blockreferralspam.egg-info/SOURCES.txt
django_blockreferralspam.egg-info/dependency_links.txt
django_blockreferralspam.egg-info/not-zip-safe
django_blockreferralspam.egg-info/top_level.txt