Metadata-Version: 1.1
Name: django-blockreferralspam
Version: 0.0.1
Summary: Django application to block referrall spam
Home-page: https://github.com/avara1986/django-blockreferralspam.git
Author: Alberto Vara
Author-email: a.vara.1986@gmail.com
License: LGPL 3
Keywords: django,spam,block
Platform: UNKNOWN
Classifier: Development Status :: 4 - Beta
Classifier: Environment :: Web Environment
Classifier: Framework :: Django
Classifier: Intended Audience :: Developers
Classifier: License :: OSI Approved :: GNU Library or Lesser General Public License (LGPL)
Classifier: Programming Language :: Python
Classifier: Programming Language :: Python :: 2
Classifier: Programming Language :: Python :: 3
